examples/example.ipynb
examples/example_movements.ipynb
examples/validation.ipynb
paper/fig_calibrations.pdf
paper/fig_flowVSvol.pdf
paper/fig_sinus.pdf
paper/paper.bib
paper/paper.md
paper/paper.pdf
pybreathe/__init__.py
pybreathe/base/__init__.py
pybreathe/base/breathingflow.py
pybreathe/base/breathingmovement.py
pybreathe/base/breathingsignals.py
pybreathe/base/coherence.py
pybreathe/base/featureextraction.py
pybreathe/base/instantiationmethods.py
pybreathe/base/utils.py
pybreathe/base/visualization.py
pybreathe/datasets/__init__.py
pybreathe/datasets/breathing_like_signal_01.txt
pybreathe/datasets/breathing_like_signal_02.txt
pybreathe/datasets/readme.txt
pybreathe/datasets/sinus.txt
pybreathe-0.2.2.dist-info/licenses/LICENSE
pybreathe-0.2.2.dist-info/METADATA
pybreathe-0.2.2.dist-info/WHEEL
pybreathe-0.2.2.dist-info/top_level.txt
pybreathe-0.2.2.dist-info/RECORD
