Metadata-Version: 2.4
Name: pybreathe
Version: 0.2.2
Summary: A python package for respiratory air flow rates analysis
Author-email: Thibaut Coustillet <thib.coustillet@gmail.com>
License-Expression: MIT
Project-URL: Homepage, https://github.com/tcoustillet/pybreathe
Project-URL: Source, https://github.com/tcoustillet/pybreathe
Classifier: Programming Language :: Python :: 3
Classifier: Programming Language :: Python :: 3.10
Classifier: Intended Audience :: Science/Research
Classifier: Operating System :: OS Independent
Requires-Python: >=3.10
License-File: LICENSE
Requires-Dist: matplotlib>=3.10.1
Requires-Dist: numpy>=2.2.4
Requires-Dist: openpyxl>=3.1.5
Requires-Dist: pandas>=2.2.3
Requires-Dist: scipy>=1.15.2
Requires-Dist: seaborn>=0.13.2
Requires-Dist: xlrd>=2.0.1
Requires-Dist: xlsxwriter>=3.2.6
Requires-Dist: pypdf>=6.1.0
Provides-Extra: dev
Requires-Dist: ipykernel>=6.29.5; extra == "dev"
Requires-Dist: jupyterlab>=4.4.1; extra == "dev"
Requires-Dist: pytest>=8.4.0; extra == "dev"
Requires-Dist: pylint>=3.3.5; extra == "dev"
Requires-Dist: pycodestyle>=2.13.0; extra == "dev"
Requires-Dist: pydocstyle>=6.3.0; extra == "dev"
Requires-Dist: black>=25.1.0; extra == "dev"
Dynamic: license-file
